func_adl_servicex/ServiceX.py
func_adl_servicex/__init__.py
func_adl_servicex/local_dataset.py
func_adl_servicex/util_query_ast.py
func_adl_servicex-2.2.dist-info/METADATA
func_adl_servicex-2.2.dist-info/WHEEL
func_adl_servicex-2.2.dist-info/top_level.txt
func_adl_servicex-2.2.dist-info/RECORD
