Metadata-Version: 2.1
Name: func-adl-servicex
Version: 2.2
Summary: Submit Functional Queries to a ServiceX endpoint.
Home-page: https://github.com/iris-hep/func_adl_servicex
Author: G. Watts (IRIS-HEP/UW Seattle)
Author-email: gwatts@uw.edu
Maintainer: Gordon Watts (IRIS-HEP/UW Seattle)
Maintainer-email: gwatts@uw.edu
License: TBD
Platform: Any
Classifier: Development Status :: 5 - Production/Stable
Classifier: Intended Audience :: Developers
Classifier: Intended Audience :: Information Technology
Classifier: Programming Language :: Python
Classifier: Programming Language :: Python :: 3.11
Classifier: Programming Language :: Python :: 3.10
Classifier: Programming Language :: Python :: 3.9
Classifier: Programming Language :: Python :: 3.8
Classifier: Programming Language :: Python :: 3.7
Classifier: Topic :: Software Development
Classifier: Topic :: Utilities
Requires-Python: >=3.7
Requires-Dist: func-adl (>=3.2)
Requires-Dist: qastle (>=0.10)
Requires-Dist: servicex (>=2.6.1)
Provides-Extra: local
Requires-Dist: func-adl-xAOD[local] ; extra == 'local'
Provides-Extra: test
Requires-Dist: pytest (>=3.9) ; extra == 'test'
Requires-Dist: pytest-asyncio ; extra == 'test'
Requires-Dist: pytest-mock ; extra == 'test'
Requires-Dist: pytest-cov ; extra == 'test'
Requires-Dist: coverage ; extra == 'test'
Requires-Dist: flake8 ; extra == 'test'
Requires-Dist: codecov ; extra == 'test'
Requires-Dist: autopep8 ; extra == 'test'
Requires-Dist: twine ; extra == 'test'
Requires-Dist: testfixtures ; extra == 'test'
Requires-Dist: wheel ; extra == 'test'
Requires-Dist: asyncmock ; extra == 'test'
Requires-Dist: black ; extra == 'test'
